qany/__init__.py
qany/__main__.py
qany/qany.py
qany/logx/__init__.py
qany/logx/colored_handler.py
qany/logx/logging.yaml
qany/logx/setup_logging.py
qany-0.0.2.dist-info/METADATA
qany-0.0.2.dist-info/WHEEL
qany-0.0.2.dist-info/entry_points.txt
qany-0.0.2.dist-info/top_level.txt
qany-0.0.2.dist-info/RECORD
