Metadata-Version: 2.1
Name: qany
Version: 0.0.2
Summary: this is a description
Home-page: https://github.com/zk4/qany
Author: zk
Author-email: liuzq7@gmail.com
License: BSD
Download-URL: https://github.com/zk4/qany/archive/master.zip
Keywords: best practice for python project
Platform: UNKNOWN
Classifier: Development Status :: 5 - Production/Stable
Classifier: Environment :: Console
Requires-Python: >3.0.0
Requires-Dist: pytest (==5.2.1)
Requires-Dist: setuptools (==40.6.3)
Requires-Dist: PyYAML (==5.3)
